{
    
    "dev": {
        "user": "fdp",
        "password": "fdp",
        "db": "financial_data",
        "schema": "financial_raw",
        "host": "34.82.185.252",
        "port": 30005,
        "url": "postgresql://fdp:fdp@34.82.185.252:30005/financial_data"
    },

    "old": {
        "user": "airbyte",
        "password": "airbyte",
        "db": "financial_data",
        "schema": "financial_raw",
        "host": "localhost",
        "port": 5432,
        "url": "postgresql://airbyte:airbyte@localhost:5432/financial_data"
    },

    "prod": {
        "user": "fdp",
        "password": "fdp",
        "db": "financial_data",
        "schema": "financial_raw",
        "host": "timescaledb.fdp.svc.cluster.local",
        "port": 5432,
        "url": "postgresql://fdp:fdp@timescaledb.fdp.svc.cluster.local:5432/financial_data"
    }
}